flightline/__init__.py
flightline/_version.py
flightline/cli.py
flightline/discover_cmd.py
flightline/generate.py
flightline/hud.py
flightline/learn_cmd.py
flightline/scaffold.py
flightline/discover/__init__.py
flightline/discover/detect.py
flightline/discover/diff.py
flightline/discover/heuristics.py
flightline/discover/ingest.py
flightline/discover/interpret.py
flightline/discover/observe.py
flightline/discover/schema.py
flightline/discover/trace.py
flightline/learn/__init__.py
flightline/learn/pydantic_parser.py
flightline/learn/typescript_parser.py
flightline_ai-0.1.14.dist-info/METADATA
flightline_ai-0.1.14.dist-info/WHEEL
flightline_ai-0.1.14.dist-info/entry_points.txt
flightline_ai-0.1.14.dist-info/licenses/LICENSE
flightline_ai-0.1.14.dist-info/RECORD
