Metadata-Version: 2.4
Name: flightline-ai
Version: 0.1.14
Summary: Flightline - Synthetic data generation from sample files
Project-URL: Homepage, https://github.com/flightlinehq/mono
Project-URL: Repository, https://github.com/flightlinehq/mono
Author-email: Jesse Collins <jesse@flightlinehq.com>
License: Proprietary
License-File: LICENSE
Keywords: cli,data-generation,synthetic-data,testing
Classifier: Development Status :: 4 - Beta
Classifier: Environment :: Console
Classifier: Intended Audience :: Developers
Classifier: License :: Other/Proprietary License
Classifier: Programming Language :: Python :: 3
Classifier: Programming Language :: Python :: 3.9
Classifier: Programming Language :: Python :: 3.10
Classifier: Programming Language :: Python :: 3.11
Classifier: Programming Language :: Python :: 3.12
Requires-Python: >=3.9
Requires-Dist: click>=8.1.0
Requires-Dist: httpx<0.28,>=0.27.0
Requires-Dist: openai>=1.52.0
Requires-Dist: pathspec>=0.12.0
Requires-Dist: pydantic>=2.0.0
Requires-Dist: python-dotenv>=1.0.0
Requires-Dist: rich>=13.7.0
Provides-Extra: dev
Requires-Dist: pytest>=8.0.0; extra == 'dev'
Requires-Dist: ruff>=0.1.0; extra == 'dev'
